password_stretcher/__init__.py
password_stretcher/analyzer.py
password_stretcher/lib/cap.py
password_stretcher/lib/deconstruct.py
password_stretcher/lib/errors.py
password_stretcher/lib/leet.py
password_stretcher/lib/mangler.py
password_stretcher/lib/mutator.py
password_stretcher/lib/pend.py
password_stretcher/lib/perm.py
password_stretcher/lib/policy.py
password_stretcher/lib/spider.py
password_stretcher/lib/stat/assets/styles.css
password_stretcher/lib/stat/report.py
password_stretcher/lib/stat/stat.py
password_stretcher/lib/utils.py
password_stretcher/lists/top100000_digit_special.rules
password_stretcher/stretcher.py
password_stretcher-1.0.6.dist-info/entry_points.txt
password_stretcher-1.0.6.dist-info/LICENSE
password_stretcher-1.0.6.dist-info/WHEEL
password_stretcher-1.0.6.dist-info/METADATA
password_stretcher-1.0.6.dist-info/RECORD
